{
    "boxShadow": "none",
    "widgetName": "Container2",
    "borderColor": "transparent",
    "disallowCopy": true,
    "isCanvas": true,
    "dynamicPropertyPathList": [{"key": "borderRadius"}],
    "displayName": "Container",
    "iconSVG": "/static/media/icon.1977dca3.svg",
    "topRow": 0,
    "bottomRow": 8,
    "dragDisabled": true,
    "type": "CONTAINER_WIDGET",
    "hideCard": false,
    "openParentPropertyPane": true,
    "isDeletable": false,
    "animateLoading": true,
    "leftColumn": 0,
    "dynamicBindingPathList": [],
    "children": [{
        "labelTextSize": "0.875rem",
        "boxShadow": "none",
        "widgetName": "Canvas6",
        "detachFromLayout": true,
        "displayName": "Canvas",
        "widgetId": "xmnka92wor",
        "topRow": 0,
        "bottomRow": 80,
        "containerStyle": "none",
        "parentRowSpace": 1,
        "isVisible": true,
        "type": "CANVAS_WIDGET",
        "canExtend": false,
        "version": 1,
        "hideCard": true,
        "parentId": "10nz24lgni",
        "renderMode": "CANVAS",
        "isLoading": false,
        "parentColumnSpace": 1,
        "leftColumn": 0,
        "dynamicBindingPathList": [],
        "borderRadius": "0px",
        "key": "cmiuyshrte"
    }],
    "borderWidth": "0",
    "key": "2rkzi2a87z",
    "disablePropertyPane": true,
    "labelTextSize": "0.875rem",
    "backgroundColor": "white",
    "rightColumn": 64,
    "dynamicHeight": "FIXED",
    "widgetId": "10nz24lgni",
    "containerStyle": "card",
    "isVisible": true,
    "version": 1,
    "parentId": "ajao56yblg",
    "renderMode": "CANVAS",
    "isLoading": false,
    "borderRadius": "0px",
    "maxDynamicHeight": 9000,
    "minDynamicHeight": 4
}